napalm_yang
